{
  "name": "Jasper",
  "terms": {
    "Terms of Service": {
      "fetch": "https://www.jasper.ai/legal/terms",
      "select": ".sticky_scroll_right",
      "executeClientScripts": true
    },
    "Privacy Policy": {
      "fetch": "https://www.jasper.ai/legal/privacy",
      "select": ".sticky_scroll_right",
      "executeClientScripts": true
    },
    "Acceptable Use Policy": {
      "fetch": "https://www.jasper.ai/legal/usage-policies",
      "select": ".sticky_scroll_right",
      "executeClientScripts": true
    },
    "Data Processor Agreement": {
      "fetch": "https://www.jasper.ai/legal/dpa",
      "select": ".sticky_scroll_right",
      "executeClientScripts": true
    }
  }
}
